ai_function_helper/__init__.py
ai_function_helper/helper.py
ai_function_helper-1.0.3.dist-info/METADATA
ai_function_helper-1.0.3.dist-info/WHEEL
ai_function_helper-1.0.3.dist-info/top_level.txt
ai_function_helper-1.0.3.dist-info/RECORD
