Metadata-Version: 2.1
Name: ai_function_helper
Version: 1.0.3
Summary: A helper for creating AI-powered functions using OpenAI's API
Home-page: https://github.com/Clad3815/ai-function-helper-python
Author: Clad3815
Author-email: clad3815@gmail.com
Classifier: Intended Audience :: Developers
Classifier: License :: OSI Approved :: MIT License
Classifier: Programming Language :: Python :: 3.7
Classifier: Programming Language :: Python :: 3.8
Classifier: Programming Language :: Python :: 3.9
Classifier: Programming Language :: Python :: 3.10
Requires-Python: >=3.7
Requires-Dist: openai
Requires-Dist: pydantic
Requires-Dist: jsonschema
Requires-Dist: colorama
Requires-Dist: json-repair
Requires-Dist: pillow
Requires-Dist: requests
